desktop_shop/__init__.py
desktop_shop/__main__.py
desktop_shop/crypto.py
desktop_shop/py.typed
desktop_shop/server.py
desktop_shop/user.py
desktop_shop/util.py
desktop_shop/database/__init__.py
desktop_shop/database/_statements.py
desktop_shop/database/database.py
desktop_shop/database/sql/create_or_replace_detailed_transactions_table.sql
desktop_shop/database/sql/create_or_replace_products_table.sql
desktop_shop/database/sql/create_or_replace_sessions_table.sql
desktop_shop/database/sql/create_or_replace_transactions_table.sql
desktop_shop/database/sql/create_or_replace_users_table.sql
desktop_shop/database/sql/insert_detailed_transaction.sql
desktop_shop/database/sql/insert_product.sql
desktop_shop/database/sql/insert_session.sql
desktop_shop/database/sql/insert_transaction.sql
desktop_shop/database/sql/insert_user.sql
desktop_shop/database/sql/query_last_inserted_id.sql
desktop_shop/database/sql/query_product_ids.sql
desktop_shop/database/sql/query_products.sql
desktop_shop/database/sql/query_session_by_id_and_email.sql
desktop_shop/database/sql/query_session_by_id_and_user.sql
desktop_shop/database/sql/query_user_by_email.sql
desktop_shop/database/sql/query_user_by_id.sql
desktop_shop/database/sql/query_user_id_by_email.sql
desktop_shop/database/sql/query_user_ids.sql
desktop_shop/database/sql/query_user_pw_hash_and_salt_by_email.sql
desktop_shop/database/sql/update_user_by_email.sql
desktop_shop/database/sql/update_user_by_id.sql
desktop_shop/database/sql/update_user_pw_by_email.sql
desktop_shop/datagen/__init__.py
desktop_shop/datagen/data.py
desktop_shop/datagen/generate_data.py
desktop_shop/gui/__init__.py
desktop_shop/gui/callbacks.py
desktop_shop/gui/components.py
desktop_shop/gui/config.py
desktop_shop/gui/init.py
desktop_shop/gui/views/__init__.py
desktop_shop/gui/views/checkout.py
desktop_shop/gui/views/home.py
desktop_shop/gui/views/login.py
desktop_shop/gui/views/main_menu.py
desktop_shop/gui/views/profile.py
desktop_shop/gui/views/register.py
desktop_shop-1.1.3.dist-info/LICENSE
desktop_shop-1.1.3.dist-info/METADATA
desktop_shop-1.1.3.dist-info/WHEEL
desktop_shop-1.1.3.dist-info/top_level.txt
desktop_shop-1.1.3.dist-info/RECORD
