Metadata-Version: 2.1
Name: desktop_shop
Version: 1.1.3
Summary: Desktop shop application
Home-page: https://github.com/rbaltrusch/desktop_shop
Author: Richard Baltrusch
License: MIT
Keywords: python
Classifier: Development Status :: 4 - Beta
Classifier: Intended Audience :: Developers
Classifier: Intended Audience :: Education
Classifier: License :: OSI Approved :: MIT License
Classifier: Programming Language :: Python
Classifier: Programming Language :: Python :: 3
Classifier: Programming Language :: Python :: 3 :: Only
Classifier: Programming Language :: Python :: 3.8
Classifier: Programming Language :: Python :: 3.9
Classifier: Programming Language :: Python :: 3.10
Classifier: Programming Language :: Python :: 3.11
Classifier: Topic :: Desktop Environment
Classifier: Topic :: Education
Classifier: Topic :: Education :: Testing
Classifier: Topic :: Office/Business
Classifier: Topic :: Office/Business :: Financial :: Point-Of-Sale
Classifier: Typing :: Typed
Requires-Python: >=3.8
License-File: LICENSE
Requires-Dist: wikipedia ==1.4.0
Requires-Dist: requests ==2.30.0
Requires-Dist: beautifulsoup4 ==4.12.2
